[{"start":4.938,"end":8.278,"text":"Crianças, vou lhes contar uma história fascinante:"},{"start":8.278,"end":10.645,"text":"a história sobre como conheci a sua mãe."},{"start":10.645,"end":13.042,"text":"Nós estamos sendo castigados?"},{"start":13.042,"end":13.691,"text":"Não."},{"start":13.691,"end":15.666,"text":"Isso vai demorar?"},{"start":15.666,"end":19.74,"text":"Sim. 25 anos atrás, antes de ser pai,"},{"start":19.74,"end":21.972,"text":"Eu tinha uma vida completamente diferente."},{"start":25.795,"end":27.954,"text":"Era o ano de 2005."},{"start":27.954,"end":30.873,"text":"Eu tinha 27 anos, acabava de me estabelecer como arquiteto..."},{"start":30.873,"end":33.908,"text":"e vivia em Nova Iorque com Marshall, meu melhor amigo da faculdade."},{"start":33.908,"end":35.191,"text":"Minha vida era boa."},{"start":35.191,"end":38.122,"text":"Então o tio Marshall foi e estragou tudo."},{"start":39.092,"end":40.846,"text":"Você aceita casar comigo?"},{"start":41.647,"end":42.757,"text":"Sim. Perfeito!"},{"start":42.757,"end":44.925,"text":"E então você fica noivo. Você estoura o champanhe."},{"start":44.925,"end":45.71,"text":"Você propõe um brinde."},{"start":45.71,"end":47.633,"text":"Você faz sexo no chão da cozinha."},{"start":47.633,"end":49.53,"text":"Não faça sexo no chão da nossa cozinha."},{"start":49.53,"end":50.266,"text":"Entendi."},{"start":50.266,"end":51.812,"text":"Obrigado por me ajudar a planejar tudo, Ted."},{"start":51.812,"end":54.241,"text":"Cara, você está brincando? É você e a Lilly."},{"start":54.241,"end":56.829,"text":"Estive presente em todos os grandes momentos seus com a Lilly:"},{"start":56.829,"end":61.498,"text":"a noite em que se conheceram, o primeiro encontro, outras primeiras coisas."},{"start":61.498,"end":64.435,"text":"Ah, desculpe. Achamos que estivesse dormindo."},{"start":64.435,"end":65.541,"text":"É a física, Marshall."},{"start":65.541,"end":68.416,"text":"Se a cama de cima do beliche se mexe, a de baixo se mexe também."},{"start":69.786,"end":71.117,"text":"Meu Deus."},{"start":71.978,"end":73.981,"text":"Você vai noivar hoje à noite."},{"start":74.822,"end":77.644,"text":"O que você vai fazer hoje à noite?"},{"start":78.125,"end":79.641,"text":"O que eu estava fazendo?"},{"start":79.641,"end":82.335,"text":"Aqui o tio Marshall estava dando o maior passo da sua vida."},{"start":82.335,"end":83.246,"text":"E eu?"},{"start":83.246,"end":85.299,"text":"Eu estava ligando para o seu tio Barney."},{"start":85.445,"end":88.738,"text":"Você sabe como eu sempre tive essa coisa com garotas meio asiáticas, não sabe?"},{"start":89.976,"end":94.084,"text":"Bem, agora tenho uma nova favorita... garotas libanesas."},{"start":94.084,"end":96.371,"text":"Garotas libanesas são as novas meio asiáticas."},{"start":96.995,"end":98.425,"text":"Ei, você quer fazer algo hoje à noite?"},{"start":98.425,"end":101.678,"text":"Certo, me encontre no bar em 15 minutos. E com o seu terno!"},{"start":105.661,"end":106.908,"text":"Onde está o seu terno?"},{"start":106.908,"end":109.657,"text":"Pelo menos uma vez, quando digo para colocar o terno, gostaria que você colocasse um."},{"start":109.657,"end":111.494,"text":"Eu fiz isso uma vez."},{"start":111.494,"end":113.747,"text":"Era um blazer!"},{"start":114.699,"end":118.215,"text":"Sabe, desde a faculdade temos sido, Marshall, Lilly e eu."},{"start":118.429,"end":121.188,"text":"Agora, será Marshall e Lilly... e eu."},{"start":121.188,"end":122.92,"text":"Eles vão se casar, começar uma família."},{"start":122.92,"end":127.752,"text":"Agora, eu sou esse estranho solteirão de meia-idade que seus filhos chamam tio Ted."},{"start":129.853,"end":131.334,"text":"Já sei do que se trata."},{"start":131.334,"end":133.768,"text":"Você se esqueceu do que te disse na noite que nos conhecemos?"},{"start":135.995,"end":138.613,"text":"Ted, vou te ensinar como viver."},{"start":139.343,"end":141.335,"text":"Barney. Nos conhecemos no banheiro."},{"start":141.335,"end":142.761,"text":"Ah, sim. Claro."},{"start":142.761,"end":144.854,"text":"Primeira lição: tirar o cavanhaque."},{"start":144.854,"end":146.066,"text":"Não combina com o seu terno."},{"start":146.066,"end":148.885,"text":"- Não estou vestindo um terno. - Segunda lição: comprar um terno."},{"start":148.885,"end":150.787,"text":"Ternos são legais. Imagem nota 10."},{"start":151.467,"end":156.035,"text":"Terceira lição: nem pense em se casar antes dos 30."},{"start":156.595,"end":158.412,"text":"30. Claro. Você tem razão."},{"start":158.412,"end":160.31,"text":"Acho que, por seu melhor amigo estar noivo,"},{"start":160.31,"end":161.623,"text":"você começa a pensar nessas coisas."},{"start":161.623,"end":163.374,"text":"Pensei que eu fosse o seu melhor amigo."},{"start":163.774,"end":166.848,"text":"Ted, diga que sou o seu melhor amigo."},{"start":167.895,"end":168.96,"text":"Você é o meu melhor amigo, Barney."},{"start":168.96,"end":169.869,"text":"Bom. Então, como seu melhor amigo,"},{"start":169.869,"end":171.762,"text":"sugiro que joguemos um jogo que gosto de chamar..."},{"start":171.762,"end":173.93,"text":"- \"Você conhece o Ted?\" - Espere. Não, não."},{"start":173.93,"end":175.086,"text":"Nós não vamos jogar \"Você conhece o Ted?\""},{"start":175.086,"end":176.552,"text":"Oi, você conhece o Ted?"},{"start":177.295,"end":179.775,"text":"Oi, eu sou o Ted."},{"start":179.775,"end":180.7,"text":"Yasmine."},{"start":180.7,"end":182.031,"text":"Esse é um nome muito bonito."},{"start":182.031,"end":183.923,"text":"Obrigado. É libanês."},{"start":189.414,"end":190.851,"text":"Estou exausta."},{"start":190.851,"end":192.554,"text":"Era dia de pintura à dedo na escola,"},{"start":192.554,"end":196.436,"text":"e um garoto de 5 anos chegou à segunda base comigo."},{"start":197.795,"end":199.534,"text":"Nossa! Você está cozinhando?"},{"start":199.534,"end":201.267,"text":"Sim, estou."},{"start":201.267,"end":202.419,"text":"Ah..."},{"start":203.751,"end":205.088,"text":"Você tem certeza que é uma boa idéia?"},{"start":205.088,"end":208.314,"text":"Da última vez, você ficou realmente assustador sem as sobrancelhas."},{"start":208.905,"end":209.73,"text":"Posso cuidar disso."},{"start":209.73,"end":212.104,"text":"Você vai descobrir que estou cheio de surpresas hoje à noite."},{"start":212.104,"end":214.533,"text":"Então, tem mais surpresas? Como o quê?"},{"start":214.695,"end":216.674,"text":"Marshall estava no 2º ano da faculdade de Direito."},{"start":216.674,"end":219.156,"text":"Então ele era muito bom em pensar respostas rápidas."},{"start":219.156,"end":220.515,"text":"Boogedyboo !"},{"start":220.995,"end":222.346,"text":"E isso é tudo."},{"start":224.152,"end":226.064,"text":"Eu vou... cozinhar."},{"start":226.795,"end":228.581,"text":"Estou tão feliz pelo Marshall, eu realmente estou."},{"start":228.581,"end":230.858,"text":"Eu só não me imagino fazendo o mesmo neste momento."},{"start":230.858,"end":232.51,"text":"Você acha que vai se casar algum dia?"},{"start":232.895,"end":234.447,"text":"Bem, talvez eventualmente..."},{"start":234.653,"end":237.702,"text":"algum dia de outono, no Central Park."},{"start":238.345,"end":240.433,"text":"Cerimônia simples. Nós escreveremos nossos votos."},{"start":240.995,"end":242.615,"text":"Banda, sem DJ. Pessoas dançando!"},{"start":242.615,"end":244.368,"text":"Não vou me preocupar com isso!"},{"start":245.437,"end":247.865,"text":"Droga, por quê Marshall tinha que ficar noivo?"},{"start":248.576,"end":251.965,"text":"Nada mais excitante do que um cara planejando seu próprio casamento imaginário, certo?"},{"start":251.965,"end":255.635,"text":"- Na verdade, eu acho bonitinho. - Bom, claramente você está bêbada."},{"start":256.03,"end":257.571,"text":"Mais um para a garota!"},{"start":258.995,"end":260.35,"text":"Ah, veja o que eu consegui."},{"start":264.336,"end":267.485,"text":"Ah, querido! Champanhe."},{"start":268.732,"end":269.621,"text":"sim."},{"start":271.113,"end":275.139,"text":"Não. Você é velho demais para ter medo de abrir uma garrafa de champanhe."},{"start":275.139,"end":276.857,"text":"- Não tenho medo. - Então abra."},{"start":276.857,"end":277.947,"text":"Certo."},{"start":279.605,"end":280.826,"text":"Você pode abrir, por favor?"},{"start":281.296,"end":283.143,"text":"Você é inacreditável, Marshall."},{"start":283.143,"end":285.767,"text":"Há duas grandes questões que o homem deve se perguntar na vida."},{"start":285.767,"end":287.549,"text":"Uma, você planeja durante meses."},{"start":287.549,"end":290.523,"text":"A outra sai somente quando você está meio bêbado em algum bar."},{"start":290.523,"end":291.915,"text":"Você aceita casar comigo?"},{"start":291.915,"end":293.328,"text":"Você quer sair algum dia?"},{"start":294.038,"end":296.02,"text":"Claro, seu idiota!"},{"start":297.062,"end":299.831,"text":"Desculpe, Carl é o meu namorado."},{"start":302.312,"end":303.524,"text":"E aí, Carl?"},{"start":307.796,"end":309.929,"text":"Prometi ao Ted que não faríamos isso."},{"start":310.958,"end":313.716,"text":"Você sabia que tem um Pop Tart embaixo da sua geladeira?"},{"start":313.716,"end":315.379,"text":"Não mesmo."},{"start":316.35,"end":318.032,"text":"Onde está aquele champanhe?"},{"start":318.753,"end":322.214,"text":"Quero tomar um brinde com minha noiva."},{"start":325.095,"end":327.133,"text":"Eu não sei porque estava com medo disso."},{"start":327.563,"end":329.145,"text":"É muito fácil, não é?"},{"start":331.834,"end":333.482,"text":"Por que estou surtando de repente?"},{"start":333.482,"end":335.86,"text":"Isso é loucura. Não estou pronto para isso."},{"start":335.86,"end":338.404,"text":"Como Carl consegue uma garota libanesa?"},{"start":338.945,"end":341.64,"text":"O plano sempre foi, não pensar nisso até os 30."},{"start":341.64,"end":343.875,"text":"Exato. O cara nem sequer tem um terno."},{"start":344.445,"end":346.424,"text":"Além disso, Marshall encontrou o amor da sua vida."},{"start":346.424,"end":348.587,"text":"Mesmo que eu estivesse preparado, o que não estou..."},{"start":348.587,"end":353.273,"text":"mas se estivesse, seria, como... \"Certo, estou pronto. Onde ela está?\""},{"start":357.595,"end":359.494,"text":"E lá estava ela."},{"start":365.164,"end":367.047,"text":"Foi como um filme antigo,"},{"start":367.047,"end":370.438,"text":"onde o marinheiro vê a garota do outro lado da pista de dança,"},{"start":370.438,"end":373.382,"text":"vira para o seu amigo e diz, \"Está vendo essa garota?"},{"start":373.382,"end":375.525,"text":"Vou me casar com ela algum dia."},{"start":375.879,"end":378.459,"text":"Ei, Barney, vê essa garota?"},{"start":378.459,"end":381.37,"text":"Ah, sim. Dá pra perceber que ela gosta de pegar pesado."},{"start":382.043,"end":383.018,"text":"Vá dizer oi."},{"start":383.528,"end":384.97,"text":"Não posso apenas ir dizer oi."},{"start":384.97,"end":386.241,"text":"Preciso de um plano."},{"start":386.241,"end":388.377,"text":"Vou esperar até que ela vá ao banheiro,"},{"start":388.377,"end":390.413,"text":"então eu estrategicamente irei até o aparelho de som..."},{"start":390.413,"end":391.884,"text":"Oi, você conhece o Ted?"},{"start":395.959,"end":398.823,"text":"Deixe-me adivinhar... Ted."},{"start":401.493,"end":403.912,"text":"Desculpa, Lilly. Sinto muito."},{"start":403.912,"end":406.206,"text":"- Leve-nos ao hospital. - Whoa, whoa, whoa."},{"start":406.206,"end":407.528,"text":"Você bateu nela?"},{"start":409.209,"end":410.871,"text":"Bater em mim? Por favor!"},{"start":410.871,"end":413.916,"text":"Esse cara mal consegue me dar uns tapinhas na cama por diversão."},{"start":413.916,"end":416.596,"text":"Ele é do tipo: \"Ah, querida. Isso doeu?\""},{"start":416.596,"end":419.391,"text":"E eu sou mais do tipo: \"Qual é! Me dê um pouco, seu frouxo!\""},{"start":420.431,"end":423.031,"text":"- Um completo estranho. - Não, não, não! Tudo bem."},{"start":423.031,"end":423.941,"text":"Vá em frente."},{"start":424.402,"end":426.1,"text":"Então, esses... tapinhas..."},{"start":426.1,"end":429.095,"text":"você fica de pijama ou ao natural?"},{"start":430.593,"end":431.539,"text":"Então, o que você faz?"},{"start":431.539,"end":433.713,"text":"Sou repórter do Notícias Metro One."},{"start":433.713,"end":435.988,"text":"Quer dizer, meio que uma repórter."},{"start":435.988,"end":438.457,"text":"Faço aquelas pontinhas bobas no final das notícias."},{"start":438.457,"end":439.95,"text":"Você sabe, como um..."},{"start":440.531,"end":442.575,"text":"macaco que sabe jogar o \"ukulele\"."},{"start":442.67,"end":444.765,"text":"Espero conseguir maiores histórias logo."},{"start":444.765,"end":447.571,"text":"Maiores, que... sabe, um gorila tocando contra-baixo?"},{"start":448.352,"end":450.015,"text":"Desculpa. Você é realmente bonita."},{"start":454.043,"end":455.721,"text":"Suas amigas não parecem muito contentes."},{"start":455.721,"end":457.98,"text":"Ah, bem, a do meio acaba de levar um fora do seu namorado."},{"start":457.98,"end":460.594,"text":"Hoje à noite, todos os caras serão \"inimigos\"."},{"start":460.948,"end":462.135,"text":"Sabe... se isso fizer a sua amiga se sentir melhor,"},{"start":462.135,"end":464.358,"text":"você pode até jogar um drinque na minha cara. Eu não me importo."},{"start":464.752,"end":466.37,"text":"Ela adoraria isso!"},{"start":466.893,"end":468.812,"text":"Parece ser divertido nos filmes."},{"start":469.493,"end":471.095,"text":"Você quer jantar comigo no sábado à noite?"},{"start":471.095,"end":472.356,"text":"Não posso."},{"start":472.356,"end":474.469,"text":"Eu vou para Orlando por uma semana na sexta."},{"start":474.469,"end":476.932,"text":"Algum cara tentando fazer a maior panqueca do mundo."},{"start":476.932,"end":478.496,"text":"Adivinha quem estará cobrindo?"},{"start":478.496,"end":479.637,"text":"Isso vai levar uma semana?"},{"start":479.637,"end":481.674,"text":"Sim, ele vai comer isso também. É um outro recorde."},{"start":482.058,"end":484.252,"text":"Por que está demorando tanto?"},{"start":485.088,"end":487.973,"text":"Sei que é um pouco de atrevimento, mas... que tal amanhã à noite?"},{"start":489.393,"end":491.917,"text":"Sim. Por quê não?"},{"start":497.393,"end":498.449,"text":"Babaca!"},{"start":499.593,"end":500.76,"text":"Isso foi divertido."},{"start":502.071,"end":504.92,"text":"Ne... espere por isso... gado!"},{"start":504.92,"end":506.392,"text":"Negado!"},{"start":506.836,"end":508.164,"text":"Nós vamos sair amanhã à noite."},{"start":508.164,"end":510.678,"text":"Pensei que fôssemos jogar mira laser amanhã à noite."},{"start":510.678,"end":513.272,"text":"Eu nunca vou jogar mira laser."},{"start":516.493,"end":519.935,"text":"Na noite seguinte, a levei até um pequeno bistrô no Brooklyn."},{"start":521.367,"end":523.696,"text":"Essa é uma baita trompeta azul francesa."},{"start":523.696,"end":524.351,"text":"Sim."},{"start":524.702,"end":527.166,"text":"Até que parece o pênis de um Smurf."},{"start":528.193,"end":529.911,"text":"Filho, um pequeno conselho:"},{"start":529.911,"end":533.528,"text":"Quando você for a um primeiro encontro, não diga coisas como \"pênis de um Smurf\"."},{"start":533.873,"end":536.077,"text":"Garotas não costumam gostar disso."},{"start":537.5,"end":540.67,"text":"Mas ela não era uma garota como as outras."},{"start":544.544,"end":545.302,"text":"Lilly?"},{"start":546.946,"end":549.13,"text":"Há quanto tempo você está sentado aí?"},{"start":549.13,"end":551.127,"text":"Estúpido tapa-olhos."},{"start":553.579,"end":557.953,"text":"Mãe, pai, eu encontrei a futura Sra. Ted Mosby."},{"start":557.953,"end":560.342,"text":"Marshall, como eu sempre descrevi a minha mulher ideal?"},{"start":560.342,"end":563.226,"text":"Vejamos... ela gosta de cachorros?"},{"start":563.226,"end":564.768,"text":"Eu tenho 5 cachorros."},{"start":564.768,"end":565.703,"text":"Ela bebe whisky escocês?"},{"start":565.703,"end":568.72,"text":"Eu amo um escocês com idade suficiente para pedir seu próprio whisky."},{"start":568.72,"end":570.813,"text":"Ela sabe citar diálogos obscuros dos Caça-fantasmas?"},{"start":570.813,"end":574.711,"text":"Ray! Quando alguém te pergunta se você é bom, diga \"sim\"!"},{"start":575.892,"end":578.125,"text":"E estou deixando o melhor para o final."},{"start":578.125,"end":580.689,"text":"Você quer isto? Eu odeio azeitonas."},{"start":580.689,"end":582.719,"text":"Ela odeia azeitonas! Demais!"},{"start":582.719,"end":584.572,"text":"A teoria da azeitona."},{"start":584.572,"end":587.478,"text":"A teoria da azeitona é baseada nos meus amigos Marshall e Lilly."},{"start":587.478,"end":589.241,"text":"Ele odeia azeitonas, ela ama."},{"start":589.241,"end":591.185,"text":"De alguma forma, isso os torna um grande casal."},{"start":591.185,"end":592.727,"text":"Balance perfeito."},{"start":593.723,"end":597.831,"text":"Eu tenho um pote de azeitonas na minha geladeira sempre."},{"start":599.493,"end":601.08,"text":"Eu poderia tirá-las de suas mãos."},{"start":602.534,"end":603.958,"text":"São todas suas."},{"start":604.354,"end":606.127,"text":"Está valendo!"},{"start":606.127,"end":608.917,"text":"Está valendo até o amanhecer."},{"start":610.593,"end":611.428,"text":"Espera."},{"start":611.428,"end":614.073,"text":"Ainda são 22:30. O que aconteceu?"},{"start":615.029,"end":618.295,"text":"Tenho que conseguir uma dessas trompetas francesas azuis para a minha lareira."},{"start":618.295,"end":620.143,"text":"Tem que ser azul. Tem que ser francês."},{"start":620.143,"end":621.46,"text":"- Nenhum clarinete verde? - Não."},{"start":621.46,"end":623.063,"text":"Vamos. Nem uma tuba púrpura?"},{"start":623.063,"end":625.206,"text":"É um pênis de Smurf ou nada."},{"start":626.534,"end":627.505,"text":"Aí está você!"},{"start":627.505,"end":628.655,"text":"Nós temos um saltador."},{"start":628.655,"end":630.659,"text":"Algum maluco na Ponte de Manhattan."},{"start":630.659,"end":632.272,"text":"Vamos. Eles estão cobrindo!"},{"start":632.793,"end":635.166,"text":"Tudo vem. Vou ficar bem aqui."},{"start":636.347,"end":637.603,"text":"Me desculpe."},{"start":638.484,"end":640.589,"text":"Eu me diverti muito esta noite."},{"start":641.693,"end":642.76,"text":"Sim."},{"start":642.76,"end":644.843,"text":"Então? Você beijou ela?"},{"start":645.207,"end":647.115,"text":"Não. Não era o momento certo."},{"start":647.115,"end":649.463,"text":"Veja, essa mulher pode ser a minha futura esposa."},{"start":649.463,"end":651.047,"text":"Quero que nosso primeiro beijo seja incrível."},{"start":651.047,"end":653.886,"text":"Ted, isso é tão lindo."},{"start":654.266,"end":656.43,"text":"Então você fraquejou como uma garotinha."},{"start":658.183,"end":660.306,"text":"O quê? Eu não fraquejei."},{"start":660.306,"end":660.969,"text":"Sabe de uma coisa?"},{"start":660.969,"end":663.719,"text":"Não tomo conselhos sobre primeiro beijo de algum pirata"},{"start":663.719,"end":665.847,"text":"que não está solteiro desde sua primeira semana de faculdade."},{"start":665.847,"end":668.538,"text":"Qualquer solteiro te diria a mesma coisa,"},{"start":668.538,"end":671.159,"text":"até o solteiro mais burro vivo."},{"start":671.159,"end":673.682,"text":"E se você não acredita em mim, ligue para ele."},{"start":675.526,"end":676.322,"text":"Ei, perdedor."},{"start":676.322,"end":677.518,"text":"Quem não quer jogar mira laser?"},{"start":677.518,"end":679.893,"text":"Porque jogar mira laser é demais!"},{"start":680.452,"end":682.773,"text":"- Matei você, Conner! - Não me faça pegar a sua mãe!"},{"start":682.773,"end":684.943,"text":"Escuta. Preciso da tua opinião sobre uma coisa."},{"start":684.943,"end":686.57,"text":"Certo, me encontre no bar em 15 minutos."},{"start":686.57,"end":687.702,"text":"E coloque o seu terno!"},{"start":689.043,"end":691.182,"text":"Então, eles acham que eu fraquejei."},{"start":691.182,"end":692.334,"text":"O que você acha?"},{"start":692.334,"end":696.303,"text":"Não acredito que você não veste o terno ainda."},{"start":697.424,"end":698.764,"text":"Ela nem sequer me deu um sinal."},{"start":698.764,"end":701.75,"text":"O que você espera? Que ela comece a piscar em código Morse para você?"},{"start":701.75,"end":706.956,"text":"\"Ted... me beija.\" Não! Você simplesmente a beija!"},{"start":706.956,"end":709.05,"text":"Não se você não recebe o sinal."},{"start":712.164,"end":713.862,"text":"Marshall me deu um sinal?"},{"start":713.862,"end":716.366,"text":"Não! Eu não. Eu juro."},{"start":718.304,"end":719.441,"text":"Mas, pelo menos hoje,"},{"start":719.441,"end":721.064,"text":"Vou me deitar sabendo que o lance com Marshall,"},{"start":721.064,"end":721.879,"text":"nunca vai rolar."},{"start":721.879,"end":723.206,"text":"Você deveria tê-la beijado."},{"start":723.813,"end":725.33,"text":"Ah, eu deveria tê-la beijado."},{"start":725.33,"end":727.52,"text":"Bom, talvez semana que vem quando ela voltar de Orlando."},{"start":727.52,"end":729.885,"text":"Uma semana? Isso é um ano na vida das garotas gostosas."},{"start":729.885,"end":731.153,"text":"Ela vai se esquecer de você."},{"start":731.153,"end":734.63,"text":"Grave minhas palavras... você nunca mais a verá novamente."},{"start":735.11,"end":736.302,"text":"Aí está ela."},{"start":736.302,"end":739.479,"text":"Ah! Ela é uma gatinha. Ei, Carl, aumenta o volume."},{"start":739.479,"end":741.531,"text":"...o convenceu a reconsiderar."},{"start":741.531,"end":743.685,"text":"Neste momento, o homem desistiu de pular,"},{"start":743.685,"end":746.702,"text":"dando a esta bizarra história um final feliz."},{"start":746.702,"end":749.243,"text":"- Informando para a Metro One Notícias... - O cara não pulou."},{"start":750.958,"end":752.33,"text":"Eu vou beijá-la."},{"start":752.715,"end":753.52,"text":"Agora mesmo."},{"start":753.52,"end":754.963,"text":"Olha, cara. É meia-noite."},{"start":754.963,"end":758.88,"text":"Como seu futuro advogado, vou avisando que isso é muito louco."},{"start":758.88,"end":760.428,"text":"Eu nunca faço nada louco."},{"start":760.428,"end":763.079,"text":"Eu sempre espero pelo momento, planejo o momento."},{"start":763.488,"end":764.514,"text":"Bom, ela vai embora amanhã."},{"start":764.514,"end":766.077,"text":"Este pode ser o único momento que vou ter."},{"start":766.677,"end":768.004,"text":"Vou fazer o que aquele cara não conseguiu."},{"start":768.004,"end":769.772,"text":"Eu vou pular de cabeça!"},{"start":770.774,"end":772.053,"text":"Não foi uma metáfora apropriada,"},{"start":772.053,"end":773.621,"text":"porque para mim é se apaixonar e casar,"},{"start":773.621,"end":775.757,"text":"e para ele é... a morte."},{"start":776.71,"end":778.483,"text":"Na verdade, foi uma metáfora perfeita."},{"start":779.068,"end":781.27,"text":"Por certo, eu parabenizei vocês?"},{"start":782.948,"end":784.478,"text":"Vou fazer isso."},{"start":784.813,"end":785.738,"text":"Vamos."},{"start":785.738,"end":787.573,"text":"- Vamos. - Nós vamos contigo."},{"start":788.543,"end":789.461,"text":"Barney?"},{"start":790.913,"end":793.238,"text":"Tudo bem, mas sob uma condição."},{"start":794.743,"end":797.432,"text":"Olha só, seu lindo filho da mãe. Você está de terno!"},{"start":797.432,"end":799.28,"text":"Isso vai parar no meu blog!"},{"start":800.581,"end":801.318,"text":"Pare o carro."},{"start":801.318,"end":802.821,"text":"Ah, pare aqui."},{"start":804.343,"end":805.747,"text":"Tenho que fazer uma coisa."},{"start":806.601,"end":808.684,"text":"Com licença. Me desculpe, um segundo."},{"start":809.164,"end":810.376,"text":"Aproveite seu café."},{"start":812.659,"end":814.073,"text":"Vá! Vá!"},{"start":816.931,"end":818.86,"text":"Todo mundo leva flores."},{"start":825.691,"end":826.773,"text":"Certo."},{"start":826.773,"end":828.026,"text":"É a hora da verdade."},{"start":828.996,"end":830.059,"text":"Desejem-me sorte."},{"start":830.059,"end":832.994,"text":"Ted vai mandar ver com a repórter."},{"start":832.994,"end":835.553,"text":"\"Ao vivo\". Tudo bem."},{"start":838.692,"end":840.641,"text":"Beija ela, Ted! Beija gostoso!"},{"start":840.641,"end":842.069,"text":"Arranca um pedaço dessa garota!"},{"start":842.069,"end":844.289,"text":"Marshall, lembre-se dessa noite."},{"start":844.289,"end":846.554,"text":"Quando você for o padrinho do nosso casamento,"},{"start":846.554,"end":848.758,"text":"e der um discurso, você vai contar essa história."},{"start":850.481,"end":852.245,"text":"Por que ele tem que ser o padrinho?"},{"start":852.245,"end":854.389,"text":"Sou o seu melhor amigo!"},{"start":855.367,"end":858.985,"text":"À medida que entrava pela porta, um milhão de pensamentos passavam pela minha cabeça."},{"start":858.985,"end":861.57,"text":"Infelizmente, um em particular não passou."},{"start":861.57,"end":863.423,"text":"Eu tenho 5 cachorros."},{"start":865.523,"end":867.008,"text":"Nada bom. Nada bom."},{"start":867.008,"end":868.753,"text":"- Não! - Volte aqui!"},{"start":868.753,"end":870.447,"text":"Você está vestindo terno!"},{"start":873.865,"end":875.192,"text":"Ted?"},{"start":876.229,"end":877.13,"text":"Oi."},{"start":879.753,"end":881.207,"text":"Eu estava apenas..."},{"start":885.423,"end":886.73,"text":"Pode vir."},{"start":889.124,"end":889.976,"text":"Ele está dentro."},{"start":891.356,"end":892.368,"text":"Então..."},{"start":892.368,"end":895.675,"text":"Ranjit, você deve ter feito com uma garota libanesa?"},{"start":895.675,"end":898.009,"text":"Chega, não aguento mais."},{"start":898.009,"end":900.653,"text":"Vou ver se por aqui tem um banheiro."},{"start":901.403,"end":904.399,"text":"Na verdade, sou de Bangladesh."},{"start":904.399,"end":905.973,"text":"As mulheres são gostosas lá?"},{"start":905.973,"end":908.406,"text":"Aqui está uma foto da minha esposa."},{"start":910.472,"end":912.506,"text":"Um \"não\" seria suficiente."},{"start":913.738,"end":915.206,"text":"Ela é adorável."},{"start":916.517,"end":921.381,"text":"Ted, o que o traz de volta ao Brooklyn com um terno à 1 da manhã?"},{"start":922.623,"end":924.603,"text":"Eu estava esperando poder..."},{"start":925.373,"end":926.841,"text":"pegar aquelas azeitonas..."},{"start":927.312,"end":928.765,"text":"que você disse que eu poderia."},{"start":929.466,"end":931.952,"text":"Você gostaria delas em algum drinque?"},{"start":932.486,"end":934.579,"text":"Você está tentando me embebedar?"},{"start":938.715,"end":940.067,"text":"Para começar."},{"start":947.715,"end":951.297,"text":"Marshall, a teoria da azeitona, se baseia em você e a Lilly?"},{"start":951.297,"end":952.925,"text":"Você odeia azeitonas."},{"start":952.925,"end":954.949,"text":"Lilly adora Você nem suporta."},{"start":954.949,"end":956.361,"text":"É. Odeio azeitonas."},{"start":956.361,"end":961.197,"text":"Há duas semanas, no bar espanhol da rua 79, porção de azeitonas, você se serviu... e aí?"},{"start":964.623,"end":967.766,"text":"Você tem que jurar que isso não sai deste táxi."},{"start":967.766,"end":969.859,"text":"- Eu juro. - Eu juro."},{"start":971.852,"end":974.452,"text":"No nosso primeiro encontro, pedi uma salada grega."},{"start":974.452,"end":976.433,"text":"Lilly perguntou se ela poderia pegar minhas azeitonas."},{"start":976.433,"end":980.932,"text":"- Eu disse: \"Claro. Eu odeio azeitonas.\" - Mas, você gosta de azeitonas."},{"start":980.932,"end":983.522,"text":"Bem, eu tinha 18 anos, certo? E continuava virgem."},{"start":983.522,"end":986.874,"text":"Esperei minha vida inteira que uma linda garota quisesse minhas azeitonas."},{"start":988.031,"end":990.596,"text":"Marshall, vou te dar um presente de casamento antecipado."},{"start":991.187,"end":992.841,"text":"Não se case."},{"start":1001.523,"end":1003.532,"text":"Acho que gosto da sua teoria das azeitonas."},{"start":1004.123,"end":1006.312,"text":"Acho que gosto da sua nova trompeta francesa."},{"start":1007.362,"end":1009.26,"text":"Acho que gosto do seu nariz."},{"start":1010.531,"end":1012.555,"text":"Acho que estou apaixonado por você."},{"start":1012.555,"end":1015.381,"text":"O quê?!"},{"start":1016.123,"end":1017.923,"text":"Qual é, cara, você disse que sua barriga estava doendo, não foi?"},{"start":1017.923,"end":1019.294,"text":"Você sabe o que quer dizer."},{"start":1019.294,"end":1020.06,"text":"Fome."},{"start":1020.06,"end":1021.984,"text":"Você está faminto por experiências."},{"start":1021.984,"end":1023.556,"text":"Faminto por algo novo."},{"start":1023.556,"end":1025.722,"text":"Faminto por azeitonas."},{"start":1026.161,"end":1028.956,"text":"Mas está assustado demais para fazer algo à respeito."},{"start":1028.956,"end":1030.889,"text":"Estou assustado, não é?"},{"start":1032.481,"end":1034.967,"text":"Mas, quando penso em passar o resto da minha vida com Lilly..."},{"start":1035.577,"end":1038.594,"text":"compromisso, para sempre, nenhuma outra garota..."},{"start":1039.194,"end":1041.127,"text":"não me assusta nem um pouco."},{"start":1041.879,"end":1043.941,"text":"Vou me casar com essa garota."},{"start":1045.405,"end":1046.64,"text":"Lilly."},{"start":1047.592,"end":1049.377,"text":"Lilly, eu gosto de azeitonas."},{"start":1050.167,"end":1051.98,"text":"Nós faremos com que dê certo."},{"start":1064.245,"end":1066.619,"text":"Então, para Orlando. Você vai visitar a Disneyworld?"},{"start":1068.323,"end":1070.042,"text":"Você está apaixonado por mim?"},{"start":1070.752,"end":1072.508,"text":"E-eu não acredito que disse isso."},{"start":1072.508,"end":1075.074,"text":"Por quê eu falei isso? Quem disse isso?"},{"start":1075.614,"end":1077.042,"text":"Eu tenho que ir."},{"start":1077.042,"end":1078.239,"text":"Espera."},{"start":1078.239,"end":1079.711,"text":"Espera um minuto."},{"start":1082.325,"end":1083.606,"text":"Te prometi estas."},{"start":1083.606,"end":1086.727,"text":"Azeitonas. Obrigado. Eu amo você."},{"start":1086.727,"end":1088.798,"text":"O que há de errado comigo?"},{"start":1090.615,"end":1091.813,"text":"Por que ainda estamos sentados aqui?"},{"start":1091.813,"end":1093.514,"text":"Vamos. Ainda podemos tomar uma saideira."},{"start":1093.514,"end":1094.412,"text":"O que você me diz, Lil?"},{"start":1094.412,"end":1097.063,"text":"Uma garrafa de Rum?"},{"start":1099.605,"end":1100.837,"text":"Porque você é um pirata."},{"start":1101.282,"end":1103.236,"text":"Certo, tapa-olhos, fora."},{"start":1103.723,"end":1106.063,"text":"Mas não podemos largar o Ted."},{"start":1106.063,"end":1108.919,"text":"Se não for legal lá em cima, ele vai precisar de ajuda."},{"start":1108.919,"end":1110.806,"text":"Já fazem 20 minutos."},{"start":1110.806,"end":1112.163,"text":"Você acha que eles estão fazendo?"},{"start":1112.163,"end":1113.6,"text":"Você acha que eles estão fazendo na frente dos cachorros?"},{"start":1113.6,"end":1114.963,"text":"Estilo cachorrinho."},{"start":1115.307,"end":1117.426,"text":"Ei, tinha uma garota na faculdade, ela tinha um golden retriever que..."},{"start":1117.426,"end":1119.967,"text":"Está bem, nós vamos ao bar. Mas pode parar de falar."},{"start":1119.967,"end":1121.201,"text":"Manda ver, Raijit."},{"start":1126.823,"end":1128.694,"text":"Então, quando você contar essa história para os seus amigos,"},{"start":1128.694,"end":1130.858,"text":"você pode evitar a palavra \"maníaco\"?"},{"start":1131.243,"end":1133.931,"text":"Eu prefiro \"excêntrico.\""},{"start":1134.123,"end":1136.542,"text":"Boa noite... maníaco."},{"start":1140.945,"end":1141.722,"text":"Ótimo."},{"start":1141.722,"end":1143.504,"text":"Como eu chego no trem F?"},{"start":1143.909,"end":1148.033,"text":"Ah, siga dois quarteirões por aqui e vire à direita."},{"start":1151.423,"end":1152.688,"text":"Sabe de uma coisa?"},{"start":1154.123,"end":1155.833,"text":"Cansei de estar solteiro."},{"start":1156.302,"end":1157.745,"text":"Não sou bom nisso."},{"start":1157.745,"end":1161.577,"text":"Olha, é óbvio que você não pode dizer que ama uma garota que você acaba de conhecer."},{"start":1161.577,"end":1164.495,"text":"Mas... isso é uma droga."},{"start":1165.876,"end":1166.803,"text":"Vou te dizer uma coisa."},{"start":1166.803,"end":1170.727,"text":"Se uma mulher... não você, apenas uma mulher hipotética."},{"start":1170.727,"end":1172.59,"text":"quisesse passar isso tudo comigo,"},{"start":1173.575,"end":1175.233,"text":"Acho que daria um ótimo marido."},{"start":1175.233,"end":1177.116,"text":"Porque, eu seria bom em coisas do tipo,"},{"start":1177.116,"end":1180.724,"text":"fazê-la rir e ser um bom pai."},{"start":1182.044,"end":1184.3,"text":"E dando a ela 5 cachorros hipotéticos."},{"start":1186.061,"end":1187.418,"text":"Dando bons beijos."},{"start":1188.823,"end":1190.553,"text":"Todo mundo pensa que beija bem."},{"start":1190.553,"end":1192.191,"text":"Ah, eu tenho referências."},{"start":1193.423,"end":1194.572,"text":"Boa noite, Ted."},{"start":1201.073,"end":1203.422,"text":"E sou bom apertando mãos."},{"start":1203.422,"end":1205.988,"text":"Esse foi um ótimo aperto de mãos."},{"start":1209.523,"end":1210.728,"text":"E foi assim."},{"start":1210.728,"end":1212.612,"text":"Provavelmente nunca mais a veja."},{"start":1215.423,"end":1216.43,"text":"O quê?"},{"start":1216.43,"end":1217.67,"text":"Esse foi o sinal."},{"start":1217.67,"end":1221.575,"text":"Esse longo e demorado aperto de mãos? Você deveria tê-la beijado."},{"start":1221.82,"end":1223.872,"text":"Não existe nenhum \"sinal\"."},{"start":1224.274,"end":1226.187,"text":"Mas, claro... era um sinal."},{"start":1226.978,"end":1228.23,"text":"Sinal."},{"start":1229.244,"end":1230.797,"text":"Ah, Carl, obrigado."},{"start":1230.797,"end":1232.766,"text":"Algo que tenho que fazer."},{"start":1233.741,"end":1236.306,"text":"Você deveria tê-la beijado."},{"start":1236.661,"end":1238.805,"text":"Carl! Vocês não estavam lá."},{"start":1240.523,"end":1243.383,"text":"Eu estou tão excitada agora."},{"start":1243.743,"end":1245.046,"text":"Pessoal, falo sério."},{"start":1245.046,"end":1246.517,"text":"Eu vi o sinal."},{"start":1246.517,"end":1248.196,"text":"Isso não foi um sinal."},{"start":1248.196,"end":1250.215,"text":"Ted, não estamos mais nessa."},{"start":1251.466,"end":1254.794,"text":"- À minha noiva. - Ao futuro."},{"start":1254.794,"end":1256.707,"text":"À uma grande noite!"},{"start":1259.924,"end":1262.637,"text":"Aquele não era o sinal."},{"start":1263.39,"end":1265.058,"text":"Eu perguntei a ela anos depois."},{"start":1265.058,"end":1267.229,"text":"E, sim, aquele era o sinal."},{"start":1267.229,"end":1268.787,"text":"Eu poderia tê-la beijado."},{"start":1268.787,"end":1270.749,"text":"Mas isso é o engraçado do destino."},{"start":1270.749,"end":1272.873,"text":"Acontece quer você planeje ou não."},{"start":1272.873,"end":1274.847,"text":"Quero dizer que nunca achei que fosse ver aquela garota novamente,"},{"start":1274.847,"end":1277.697,"text":"mas acontece que eu estava cada vez mais perto do quebra-cabeças"},{"start":1277.697,"end":1279.521,"text":"e de ver a imagem se formando."},{"start":1279.521,"end":1284.08,"text":"Porque essa, crianças, é a verdadeira história sobre como conheci a sua tia Robin."},{"start":1285.471,"end":1286.803,"text":"Tia Robin?"},{"start":1286.803,"end":1288.888,"text":"Pensei que você tivesse conhecido a mãe assim!"},{"start":1288.888,"end":1291.02,"text":"Você quer relaxar? Já vou chegar lá."},{"start":1291.365,"end":1295.242,"text":"Como eu disse, é uma longa história."},{"start":1296.574,"end":1301.848,"text":"Tradução: arthurjpb DVD Resync: intell"},{"start":0.5,"end":2,"text":"<font color=\"#ffff00\" size=14>www.tvsubtitles.net</font>"}]